{
  "employees": [
    {
      "employee_name": "Adarsh Singh",
      "employee_salary": "12",
      "employee_age": "12",
      "id": 30
    },
    {
      "employee_name": "demo 2",
      "employee_salary": "1222",
      "employee_age": "111111111",
      "id": 31
    },
    {
      "employee_name": "assss",
      "employee_salary": "122333",
      "employee_age": "21",
      "id": 32
    },
    {
      "employee_name": "assss",
      "employee_salary": "122333",
      "employee_age": "21",
      "id": 33
    },
    {
      "employee_name": "adarsgg",
      "employee_salary": "123456",
      "employee_age": "12",
      "id": 34
    },
    {
      "employee_name": "Adarsh Check",
      "employee_salary": "12",
      "employee_age": "11",
      "id": 35
    },
    {
      "employee_name": "Adarsh Check",
      "employee_salary": "12",
      "employee_age": "11",
      "id": 36
    },
    {
      "employee_name": "check3",
      "employee_salary": "12",
      "employee_age": "12",
      "id": 37
    },
    {
      "employee_name": "check 4",
      "employee_salary": "12",
      "employee_age": "12",
      "id": 38
    },
    {
      "employee_name": "Adarsh Singh check",
      "employee_salary": "1200000",
      "employee_age": "25",
      "id": 39
    },
    {
      "employee_name": "adarsh check4",
      "employee_salary": "123455",
      "employee_age": "34",
      "id": 40
    },
    {
      "employee_name": "new",
      "employee_salary": "123456",
      "employee_age": "45",
      "id": 41
    },
    {
      "employee_name": "adarsh hit",
      "employee_salary": "1234566",
      "employee_age": "34",
      "id": 42
    },
    {
      "employee_name": "adarsh",
      "employee_salary": "1",
      "employee_age": "34",
      "id": 43
    },
    {
      "employee_name": "adarsh",
      "employee_salary": "1234",
      "employee_age": "45",
      "id": 44
    },
    {
      "employee_name": "adarsh",
      "employee_salary": "12345",
      "employee_age": "45",
      "id": 45
    },
    {
      "employee_name": "check 3",
      "employee_salary": "12345",
      "employee_age": "23",
      "id": 46
    },
    {
      "employee_name": "check again",
      "employee_salary": "123456",
      "employee_age": "34",
      "id": 47
    },
    {
      "employee_name": "adarsh",
      "employee_salary": "12345",
      "employee_age": "45",
      "id": 48
    },
    {
      "employee_name": "adarsh",
      "employee_salary": "12345",
      "employee_age": "45",
      "id": 49
    },
    {
      "employee_name": "asd",
      "employee_salary": "0001234",
      "employee_age": "45",
      "id": 50
    },
    {
      "employee_name": "asdarsh",
      "employee_salary": "1234",
      "employee_age": "34",
      "id": 51
    },
    {
      "employee_name": "Adarsh",
      "employee_salary": "1234",
      "employee_age": "45",
      "id": 52
    },
    {
      "employee_name": "Adarsh",
      "employee_salary": "12345",
      "employee_age": "34",
      "id": 53
    },
    {
      "employee_name": "Adarsh",
      "employee_salary": "1234",
      "employee_age": "45",
      "id": 54
    },
    {
      "employee_name": "Adarsh",
      "employee_salary": "1234",
      "employee_age": "54",
      "id": 55
    },
    {
      "employee_name": "Adarsh",
      "employee_salary": "1234",
      "employee_age": "33",
      "id": 56
    },
    {
      "employee_name": "check",
      "employee_salary": "1234",
      "employee_age": "45",
      "id": 57
    },
    {
      "employee_name": "Adarsh",
      "employee_salary": "1234",
      "employee_age": "34",
      "id": 58
    },
    {
      "employee_name": "Null",
      "employee_salary": "1234",
      "employee_age": "45",
      "id": 59
    },
    {
      "employee_name": "Adarsh",
      "employee_salary": "01234444444",
      "employee_age": "34",
      "id": 60
    },
    {
      "employee_name": "Adarsh",
      "employee_salary": "01234",
      "employee_age": "45",
      "id": 61
    },
    {
      "employee_name": "Adarsh",
      "employee_salary": "1234",
      "employee_age": "34",
      "id": 62
    },
    {
      "employee_name": "Adarsh",
      "employee_salary": "1234",
      "employee_age": "23",
      "id": 63
    },
    {
      "employee_name": "Adarsh",
      "employee_salary": "1234",
      "employee_age": "34",
      "id": 64
    },
    {
      "employee_name": "Adarsh",
      "employee_salary": "12344444",
      "employee_age": "34",
      "id": 65
    },
    {
      "employee_name": "Adarsh",
      "employee_salary": "1234",
      "employee_age": "34",
      "id": 66
    },
    {
      "employee_name": "Adarsh",
      "employee_salary": "1223333",
      "employee_age": "33",
      "id": 67
    },
    {
      "employee_name": "Adarsh",
      "employee_salary": "12345",
      "employee_age": "45",
      "id": 68
    },
    {
      "employee_name": "Adarsh",
      "employee_salary": "123444",
      "employee_age": "34",
      "id": 69
    },
    {
      "employee_name": "Adarsh",
      "employee_salary": "121333",
      "employee_age": "34",
      "id": 70
    },
    {
      "employee_name": "Adarsh",
      "employee_salary": "2222",
      "employee_age": "22",
      "id": 71
    },
    {
      "employee_name": "Adarsh",
      "employee_salary": "122333",
      "employee_age": "23",
      "id": 72
    },
    {
      "employee_name": "Adarsh",
      "employee_salary": "12333",
      "employee_age": "33",
      "id": 73
    },
    {
      "employee_name": "Adarsh",
      "employee_salary": "1233",
      "employee_age": "33",
      "id": 74
    },
    {
      "employee_name": "Adarsh",
      "employee_salary": "12344",
      "employee_age": "23",
      "id": 75
    },
    {
      "employee_name": "check",
      "employee_salary": "123",
      "employee_age": "23",
      "id": 76
    },
    {
      "employee_name": "check",
      "employee_salary": "12344",
      "employee_age": "34",
      "id": 77
    },
    {
      "employee_name": "Adarsh",
      "employee_salary": "1234",
      "employee_age": "23",
      "id": 78
    },
    {
      "employee_name": "Adarsh",
      "employee_salary": "123",
      "employee_age": "23",
      "id": 79
    },
    {
      "employee_name": "Adarsh",
      "employee_salary": "12333",
      "employee_age": "34",
      "id": 80
    },
    {
      "employee_name": "Adarsh",
      "employee_salary": "222222222222222",
      "employee_age": "22",
      "id": 81
    },
    {
      "employee_name": "Adarsh",
      "employee_salary": "12333333333",
      "employee_age": "33",
      "id": 82
    },
    {
      "employee_name": "Adarsh",
      "employee_salary": "12345",
      "employee_age": "45",
      "id": 83
    },
    {
      "employee_name": "Adarsh",
      "employee_salary": "1233444",
      "employee_age": "45",
      "id": 84
    },
    {
      "employee_name": "Adarsh",
      "employee_salary": "123456",
      "employee_age": "34",
      "id": 85
    },
    {
      "employee_name": "Adarsh",
      "employee_salary": "1234",
      "employee_age": "34",
      "id": 86
    },
    {
      "employee_name": "Adarsh",
      "employee_salary": "1234",
      "employee_age": "34",
      "id": 87
    }
  ]
}